{
    "ADULT_INIT_ITEMS": "0348215C",
    "ADULT_VALID_ITEMS": "03482164",
    "APPLY_BONK_DAMAGE": "03483354",
    "AUDIO_THREAD_INFO": "03483CAC",
    "AUDIO_THREAD_INFO_MEM_SIZE": "03483CCC",
    "AUDIO_THREAD_INFO_MEM_START": "03483CC8",
    "AUDIO_THREAD_MEM_START": "0349FB90",
    "AUTO_TRACKER_CONTEXT": "03480D6C",
    "AUTO_TRACKER_VERSION": "03480D6C",
    "BOMBCHUS_IN_LOGIC": "03480D4C",
    "BONK_LAST_FRAME": "034832A0",
    "CFG_A_BUTTON_COLOR": "0348084C",
    "CFG_A_NOTE_COLOR": "0348086A",
    "CFG_BOMBCHU_TRAIL_INNER_COLOR": "0348087C",
    "CFG_BOMBCHU_TRAIL_OUTER_COLOR": "0348087F",
    "CFG_BONK_DAMAGE": "0348329C",
    "CFG_BOOM_TRAIL_INNER_COLOR": "03480876",
    "CFG_BOOM_TRAIL_OUTER_COLOR": "03480879",
    "CFG_B_BUTTON_COLOR": "03480852",
    "CFG_CUSTOM_MESSAGE_1": "03480893",
    "CFG_CUSTOM_MESSAGE_2": "034808B3",
    "CFG_C_BUTTON_COLOR": "03480858",
    "CFG_C_NOTE_COLOR": "03480870",
    "CFG_DAMAGE_MULTIPLYER": "0348322C",
    "CFG_DEADLY_BONKS": "03483298",
    "CFG_DISPLAY_DPAD": "03480882",
    "CFG_DPAD_DUNGEON_INFO_ENABLE": "03480891",
    "CFG_DUNGEON_INFO_ENABLE": "03480D70",
    "CFG_DUNGEON_INFO_MQ_ENABLE": "03480D74",
    "CFG_DUNGEON_INFO_MQ_NEED_MAP": "03480D78",
    "CFG_DUNGEON_INFO_REWARD_ENABLE": "03480D7C",
    "CFG_DUNGEON_INFO_REWARD_NEED_ALTAR": "03480D84",
    "CFG_DUNGEON_INFO_REWARD_NEED_COMPASS": "03480D80",
    "CFG_DUNGEON_INFO_REWARD_SUMMARY_ENABLE": "03480D88",
    "CFG_DUNGEON_IS_MQ": "03480D9A",
    "CFG_DUNGEON_REWARDS": "03480D8C",
    "CFG_DUNGEON_REWARD_AREAS": "03480DC0",
    "CFG_FILE_SELECT_HASH": "03480834",
    "CFG_HEART_COLOR": "03480846",
    "CFG_MAGIC_COLOR": "03480840",
    "CFG_RAINBOW_BOMBCHU_TRAIL_INNER_ENABLED": "03480887",
    "CFG_RAINBOW_BOMBCHU_TRAIL_OUTER_ENABLED": "03480888",
    "CFG_RAINBOW_BOOM_TRAIL_INNER_ENABLED": "03480885",
    "CFG_RAINBOW_BOOM_TRAIL_OUTER_ENABLED": "03480886",
    "CFG_RAINBOW_NAVI_ENEMY_INNER_ENABLED": "0348088B",
    "CFG_RAINBOW_NAVI_ENEMY_OUTER_ENABLED": "0348088C",
    "CFG_RAINBOW_NAVI_IDLE_INNER_ENABLED": "03480889",
    "CFG_RAINBOW_NAVI_IDLE_OUTER_ENABLED": "0348088A",
    "CFG_RAINBOW_NAVI_NPC_INNER_ENABLED": "0348088D",
    "CFG_RAINBOW_NAVI_NPC_OUTER_ENABLED": "0348088E",
    "CFG_RAINBOW_NAVI_PROP_INNER_ENABLED": "0348088F",
    "CFG_RAINBOW_NAVI_PROP_OUTER_ENABLED": "03480890",
    "CFG_RAINBOW_SWORD_INNER_ENABLED": "03480883",
    "CFG_RAINBOW_SWORD_OUTER_ENABLED": "03480884",
    "CFG_SHOP_CURSOR_COLOR": "03480864",
    "CFG_SHOW_SETTING_INFO": "03480892",
    "CFG_TEXT_CURSOR_COLOR": "0348085E",
    "CHAIN_HBA_REWARDS": "03484640",
    "CHECK_FOR_BONK_CANCEL": "03483304",
    "CHECK_ROOM_MESH_TYPE": "03483424",
    "CHEST_LENS_ONLY": "03482B58",
    "CHEST_SIZE_MATCH_CONTENTS": "03495000",
    "CHEST_SIZE_TEXTURE": "03494FFC",
    "CHEST_TEXTURE_MATCH_CONTENTS": "03495004",
    "COMPLETE_MASK_QUEST": "03495054",
    "COOP_CONTEXT": "03480020",
    "COOP_VERSION": "03480020",
    "COSMETIC_CONTEXT": "0348083C",
    "COSMETIC_FORMAT_VERSION": "0348083C",
    "CURRENT_GROTTO_ID": "034839E6",
    "CURR_ACTOR_SPAWN_INDEX": "03484A80",
    "DEBUG_OFFSET": "03482E1C",
    "DISABLE_TIMERS": "03480D61",
    "DPAD_TEXTURE": "03499A90",
    "DUNGEONS_SHUFFLED": "03480D62",
    "EXTENDED_OBJECT_TABLE": "03480D2C",
    "EXTERN_DAMAGE_MULTIPLYER": "0348322D",
    "FAST_BUNNY_HOOD_ENABLED": "03480D64",
    "FAST_CHESTS": "03480D5B",
    "FIX_BROKEN_DROPS": "03480D65",
    "FONT_TEXTURE": "034985C8",
    "FREE_SCARECROW_ENABLED": "03480D54",
    "GANON_BOSS_KEY_CONDITION": "0349500C",
    "GANON_BOSS_KEY_CONDITION_COUNT": "0349500A",
    "GET_CHEST_OVERRIDE_WRAPPER": "03482B5C",
    "GET_ITEM_TRIGGERED": "03481824",
    "GILDED_CHEST_BASE_TEXTURE": "0349C290",
    "GILDED_CHEST_FRONT_TEXTURE": "0349B290",
    "GOSSIP_HINT_CONDITION": "03480D50",
    "GROTTO_EXIT_LIST": "034839A4",
    "GROTTO_LOAD_TABLE": "03483500",
    "GROTTO_RETURN_TABLE": "03483584",
    "HIDE_CHEST_WITH_INVERTED_LENS": "03482BA4",
    "INCOMING_ITEM": "03480028",
    "INCOMING_PLAYER": "03480026",
    "INITIAL_SAVE_DATA": "0348092C",
    "JABU_ELEVATOR_ENABLE": "03480D58",
    "KAKARIKO_WEATHER_FORECAST": "03495080",
    "KING_DODONGO_BONKS": "034833F0",
    "LACS_CONDITION": "03480DAC",
    "LACS_CONDITION_COUNT": "03480DB2",
    "MALON_GAVE_ICETRAP": "0348437C",
    "MALON_TEXT_ID": "03480D60",
    "MAX_RUPEES": "03495056",
    "MOVED_ADULT_KING_ZORA": "03483CEC",
    "MW_SEND_OWN_ITEMS": "0348002A",
    "NO_COLLECTIBLE_HEARTS": "03480D5A",
    "NO_ESCAPE_SEQUENCE": "03495009",
    "OCARINAS_SHUFFLED": "03480D59",
    "OPEN_KAKARIKO": "03495055",
    "OUTGOING_ITEM": "03480030",
    "OUTGOING_KEY": "0348002C",
    "OUTGOING_PLAYER": "03480032",
    "OVERWORLD_SHUFFLED": "03480D63",
    "PAYLOAD_START": "03480000",
    "PLANDOMIZER_USED": "03480D67",
    "PLAYED_WARP_SONG": "03481628",
    "PLAYER_ID": "03480024",
    "PLAYER_NAMES": "03480034",
    "PLAYER_NAME_ID": "03480025",
    "POTCRATE_TEXTURES_MATCH_CONTENTS": "03480D68",
    "RAINBOW_BRIDGE_CONDITION": "03480DA8",
    "RAINBOW_BRIDGE_COUNT": "03480DB0",
    "RANDOMIZER_RNG_SEED": "03495064",
    "RANDO_CONTEXT": "03480000",
    "RNG_SEED_INT": "03494FF4",
    "SET_BONK_FLAG": "034832D8",
    "SHOW_CHEST_WITH_INVERTED_LENS": "03482C1C",
    "SHUFFLE_BEANS": "0348345C",
    "SHUFFLE_CARPET_SALESMAN": "034846F8",
    "SHUFFLE_COWS": "03480D5C",
    "SHUFFLE_MEDIGORON": "03484754",
    "SILVER_CHEST_BASE_TEXTURE": "0349DA90",
    "SILVER_CHEST_FRONT_TEXTURE": "0349CA90",
    "SKULL_CHEST_BASE_TEXTURE": "0349F290",
    "SKULL_CHEST_FRONT_TEXTURE": "0349E290",
    "SONGS_AS_ITEMS": "03480D5D",
    "SOS_ITEM_GIVEN": "034818F0",
    "SPECIAL_DEAL_COUNTS": "03480DB8",
    "SPEED_MULTIPLIER": "03482CDC",
    "SPOILER_AVAILABLE": "03480D66",
    "START_TWINROVA_FIGHT": "03483D6C",
    "Sram_InitNewSave": "03494FF8",
    "TIME_STRING_TXT": "03480908",
    "TIME_TRAVEL_SAVED_EQUIPS": "03481E80",
    "TRIFORCE_HUNT_ENABLED": "03480DB4",
    "TRIFORCE_ICON_TEXTURE": "0349A290",
    "TRIFORCE_PIECES_REQUIRED": "03480DB6",
    "TWINROVA_ACTION_TIMER": "03483D70",
    "VERSION_STRING_TXT": "034808D4",
    "WINDMILL_SONG_ID": "03480D5E",
    "WINDMILL_TEXT_ID": "03480D5F",
    "WORLD_STRING_TXT": "034808F8",
    "a_button": "03494FC8",
    "a_note_b": "03494FB4",
    "a_note_font_glow_base": "03494F9C",
    "a_note_font_glow_max": "03494F98",
    "a_note_g": "03494FB8",
    "a_note_glow_base": "03494FA4",
    "a_note_glow_max": "03494FA0",
    "a_note_r": "03494FBC",
    "active_item_action_id": "03495034",
    "active_item_fast_chest": "03495024",
    "active_item_graphic_id": "03495028",
    "active_item_object_id": "0349502C",
    "active_item_row": "03495038",
    "active_item_text_id": "03495030",
    "active_override": "03495040",
    "active_override_is_outgoing": "0349503C",
    "adultSkeleton": "03494D1C",
    "adult_safe": "0349505E",
    "alt_overrides": "034950B0",
    "b_button": "03494FC4",
    "beating_dd": "03494FD0",
    "beating_no_dd": "03494FD8",
    "c_button": "03494FC0",
    "c_note_b": "03494FA8",
    "c_note_font_glow_base": "03494F8C",
    "c_note_font_glow_max": "03494F88",
    "c_note_g": "03494FAC",
    "c_note_glow_base": "03494F94",
    "c_note_glow_max": "03494F90",
    "c_note_r": "03494FB0",
    "cfg_item_overrides": "03495508",
    "childSkeleton": "03494C20",
    "child_safe": "0349505D",
    "collectible_mutex": "03495018",
    "collectible_override": "03495010",
    "collectible_override_flags": "0349501C",
    "collectible_scene_flags_table": "034952B0",
    "curr_scene_setup": "03495068",
    "defaultDDHeart": "03494FDC",
    "defaultHeart": "03494FE4",
    "dpad_sprite": "034926E0",
    "drop_collectible_override_flag": "03495048",
    "dummy_actor": "0349504C",
    "dungeon_count": "03494F58",
    "dungeons": "03492528",
    "empty_dlist": "03494F70",
    "extern_ctxt": "034925D4",
    "font_sprite": "034926F0",
    "freecam_modes": "03492190",
    "hash_sprites": "03494F64",
    "hash_symbols": "034925E8",
    "heap_next": "0349507C",
    "heart_sprite": "03492680",
    "icon_sprites": "03492354",
    "illegal_model": "03495060",
    "item_digit_sprite": "034926A0",
    "item_draw_table": "03492768",
    "item_overrides_count": "03495050",
    "item_table": "03493840",
    "items": "03492668",
    "items_sprite": "03492710",
    "key_counts": "03493824",
    "key_rupee_clock_sprite": "034926B0",
    "last_fog_distance": "03494F5C",
    "linkhead_skull_sprite": "03492690",
    "medals": "03492510",
    "medals_sprite": "03492720",
    "missing_dlist": "0349505C",
    "normal_dd": "03494FCC",
    "normal_no_dd": "03494FD4",
    "num_override_flags": "03495020",
    "num_to_bits": "03492628",
    "object_slots": "03498508",
    "quest_items_sprite": "03492700",
    "reward_rows": "03492504",
    "rupee_colors": "03492378",
    "satisified_pending_frames": "03495022",
    "scene_fog_distance": "03494F60",
    "setup_db": "03492740",
    "song_note_sprite": "034926C0",
    "stones_sprite": "03492730",
    "text_cursor_border_base": "03494F7C",
    "text_cursor_border_max": "03494F78",
    "text_cursor_inner_base": "03494F84",
    "text_cursor_inner_max": "03494F80",
    "text_height": "03494FEC",
    "text_width": "03494FF0",
    "texture_table": "03494E18",
    "triforce_sprite": "034926D0"
}